nexus_project/__init__.py
nexus_project/__main__.py
nexus_project/nexus.py
nexus_project/analysis/__init__.py
nexus_project/analysis/bandit.py
nexus_project/analysis/black.py
nexus_project/analysis/linter.py
nexus_project/analysis/project.py
nexus_project/app/__init__.py
nexus_project/app/display.py
nexus_project/app/tree.py
nexus_project/build_nxs/__init__.py
nexus_project/build_nxs/cx.py
nexus_project/build_nxs/pack.py
nexus_project/build_nxs/payload.py
nexus_project/build_nxs/publish.py
nexus_project/cache/direct.py
nexus_project/cache/management.py
nexus_project/cache/model.py
nexus_project/cache/sqlite.py
nexus_project/env_nxs/__init__.py
nexus_project/env_nxs/env.py
nexus_project/package/__init__.py
nexus_project/package/check.py
nexus_project/package/package.py
nexus_project/repository/repo.py
nexus_project/structure/__init__.py
nexus_project/structure/check.py
nexus_project/structure/create.py
nexus_project/structure/license.py
nexus_project/structure/structure.py
nexus_project/sys_nxs/__init__.py
nexus_project/sys_nxs/connect.py
nexus_project/sys_nxs/host.py
nexus_project/template/__init__.py
nexus_project/template/color.py
nexus_project/template/default_conf.py
nexus_project/template/default_ini
nexus_project/template/default_ini_lin
nexus_project/template/readme.py
nexus_project/template/regex.py
nexus_project/template/toml_format.py
nexus_project/template/toml_template.py
nexus_project/toml_nxs/__init__.py
nexus_project/toml_nxs/toml.py
nexus_project/toml_nxs/check/__init__.py
nexus_project/toml_nxs/check/check.py
nexus_project-1.3.1.dist-info/LICENSE
nexus_project-1.3.1.dist-info/METADATA
nexus_project-1.3.1.dist-info/WHEEL
nexus_project-1.3.1.dist-info/entry_points.txt
nexus_project-1.3.1.dist-info/top_level.txt
nexus_project-1.3.1.dist-info/RECORD
