Metadata-Version: 2.1
Name: nexus-project
Version: 1.3.1
Summary: Nexus project
Author: 
License: MIT License
Platform: ALL
License-File: LICENSE
Requires-Dist: impmagic
Requires-Dist: zpp-config
Requires-Dist: zpp-args
Requires-Dist: zpp-color
Requires-Dist: pygments
Requires-Dist: requests
Requires-Dist: psutil
Requires-Dist: Levenshtein
Requires-Dist: chardet
Requires-Dist: tomlkit
Requires-Dist: html5lib
Requires-Dist: bandit
Requires-Dist: zpp-ManagedFile
Requires-Dist: black
Requires-Dist: pylint
Requires-Dist: cx-Freeze
Requires-Dist: toml
Requires-Dist: pkginfo
Requires-Dist: requests-toolbelt
Requires-Dist: urllib3
Requires-Dist: pygit2
Requires-Dist: pexpect
Requires-Dist: pony
Requires-Dist: pyyaml
Requires-Dist: pynput
